syscall/__init__.py
syscall/syscall.py
sys_call-0.0.3.dist-info/LICENSE
sys_call-0.0.3.dist-info/METADATA
sys_call-0.0.3.dist-info/WHEEL
sys_call-0.0.3.dist-info/entry_points.txt
sys_call-0.0.3.dist-info/top_level.txt
sys_call-0.0.3.dist-info/RECORD
