Metadata-Version: 2.1
Name: sys-call
Version: 0.0.3
Summary: Linux Syscall implementations, calling conventions, and shellcode examples.
Home-page: http://github.com/lbirchler/sys-call/
Author: Lawrence Birchler
Author-email: bplyr@tutanota.com
Classifier: License :: OSI Approved :: MIT License
Classifier: Operating System :: OS Independent
Classifier: Programming Language :: Python
License-File: LICENSE
Requires-Dist: rich (>13.4.0)
